djangowiz/__init__.py
djangowiz/cli.py
djangowiz/core.py
djangowiz/templates/Dockerfile.j2
djangowiz/templates/docker-compose.dev.yml.j2
djangowiz/templates/docker-compose.prod.yml.j2
djangowiz/templates/env.dev.j2
djangowiz/templates/env.prod.j2
djangowiz/templates/multi/serializers.py.j2
djangowiz/templates/multi/viewsets.py.j2
djangowiz/templates/routes.py.j2
djangowiz/templates/single/serializers.py.j2
djangowiz/templates/single/viewsets.py.j2
djangowiz/templates/urls.py.j2
djangowiz-0.2.1.dist-info/LICENSE
djangowiz-0.2.1.dist-info/METADATA
djangowiz-0.2.1.dist-info/WHEEL
djangowiz-0.2.1.dist-info/entry_points.txt
djangowiz-0.2.1.dist-info/RECORD
