Metadata-Version: 2.1
Name: djangowiz
Version: 0.2.1
Summary: DjangoWiz: A simple and powerful toolkit to automate the generation of serializers, viewsets, URLs, and Docker configurations for your Django projects.
Home-page: https://github.com/tavallaie/DjangoWiz
License: MIT
Keywords: django,automation,toolkit,code-generation,web-development
Author: Ali Tavallaie
Author-email: a.tavallaie@gmail.com
Requires-Python: >=3.10,<4.0
Classifier: License :: OSI Approved :: MIT License
Classifier: Programming Language :: Python :: 3
Classifier: Programming Language :: Python :: 3.10
Classifier: Programming Language :: Python :: 3.11
Classifier: Programming Language :: Python :: 3.12
Requires-Dist: jinja2 (>=3.1.4,<4.0.0)
Requires-Dist: typer[all] (>=0.12.3,<0.13.0)
Project-URL: Repository, https://github.com/tavallaie/DjangoWiz
